{
  "courseId": 0,
  "courseName": "마산 한바퀴 코스",
  "courseRoute": "해양 드라마 세트장 - 창동 예술촌 - 돝섬 해상 유원지 - 마산 어시장 횟집거리",
  "courseTime": 8,
  "location": "경상도",
  "tag": ["마산", "돝섬", "어시장"],
  "viewCount": 0,
  "likeCount": 0,
  "guideName": "김동현",
  "guideText": "여행지의 설레는 마음을 어떤 곳이든 느낄 수 있도록!",
  "travelSpots": [
    {
      "id": 1,
      "name": "1. 해양 드라마 세트장",
      "position": { "lat": 35.1099097, "lng": 128.5413306 }
    },
    {
      "id": 2,
      "name": "2. 창동 예술촌",
      "position": { "lat": 35.2066907, "lng": 128.5741251 }
    },
    {
      "id": 3,
      "name": "3. 돝섬 해상 유원지",
      "position": { "lat": 35.178936, "lng": 128.5811386 }
    },
    {
      "id": 4,
      "name": "4. 마산 어시장 횟집거리",
      "position": { "lat": 35.2245245, "lng": 128.5795397 }
    }
  ],
  "sleeps": [
    {
      "id": 1,
      "name": "HOTEL701",
      "position": { "lat": 35.217634, "lng": 128.588129 }
    },
    {
      "id": 2,
      "name": "브라운도트 마산오동점",
      "position": { "lat": 35.204339, "lng": 128.588125 }
    },
    {
      "id": 3,
      "name": "PASTA",
      "position": { "lat": 35.205445, "lng": 128.579569 }
    }
  ],
  "eats": [
    {
      "eatId": 1,
      "name": "피노키오(양식점)",
      "position": { "lat": 35.2063203, "lng": 128.5745582 }
    },
    {
      "eatId": 2,
      "name": "사랑이 그린세상(카페)",
      "position": { "lat": 35.2071277, "lng": 128.5754999 }
    },
    {
      "eatId": 3,
      "name": "운지식당",
      "position": { "lat": 35.200633, "lng": 128.576983 }
    }
  ],

  "pathCoordinates": [
    {
      "id": 1,
      "route1": [35.1099097, 128.5413306],
      "route2": [35.2066907, 128.5741251]
    },
    {
      "id": 2,
      "route1": [35.2066907, 128.5741251],
      "route2": [35.178936, 128.5811386]
    },
    {
      "id": 3,
      "route1": [35.178936, 128.5811386],
      "route2": [35.2245245, 128.5795397]
    }
  ],

  "courseData": [
    {
      "courseDataId": 1,
      "title": "해양드라마 세트장",
      "text": "해양드라마세트장은 타임머신을 타고 가야시대로 거슬러 가는 여행지다. 마산의 아름다운 해안을 배경으로 야철장, 선착장, 저잣거리 목조건물 25채와 선박 3척 등이 들어서 있다. 세트장에서는 옛 시대의 생활풍습과 문화를 직접 느껴볼 수 있다. 2010년 4월 조성된 이후 각종 드라마와 영화의 촬영지로 이용 중이다. 2010년 MBC 드라마 <김수로>가 처음 촬영되었고, 이후 <무사 백동수>, <기황후>, <역적:백성을 훔친 도적>, <징비록>, <육룡이 나르샤> 등의 드라마와 영화가 촬영됐다. 해양드라마세트장에서는 지금도 여전히 새로운 드라마 촬영을 위한 준비가 한창이다. 해양드라마세트장에는 예쁜 바다와 바다를 곁에 두고 걸을 수 있는 길이 있다. 향기나라 옆 숲길에서 시작해 선착장 세트장으로 돌아오는 파도소리길은 파도 소리가 예쁜 해양숲길이다. 1.7km에 이르는 파도소리길에는 전망대와 해양 데크로드도 설치됐다."
    },
    {
      "courseDataId": 2,
      "title": "창동예술촌",
      "text": "창동은 과거에 경남의 명동으로 불리던 중심가다. 2000년을 전후로 쇠락의 길을 걷다가 창동예술촌을 주축으로 새롭게 태어났다. 창원시는 창동 일대 빈 점포를 예술가들에게 무상으로 제공했고, 이를 중심으로 세계적인 조각가 문신 선생의 이름을 딴 문신예술골목, 마산 예술의 역사를 담은 마산예술흔적골목, 상점과 예술을 접목한 에꼴드창동골목이 차례로 생겨났다. 2012년에는 이들 세 골목을 하나로 묶어 창동예술촌이라 이름 지었다. 창동예술촌은 어울림센터를 중심으로 아고라광장, 창동예술체험관, 갤러리, 그리고 50여 개 공방이 골목 사이사이에 자리한다. 1955년 문을 열어 국내에서 가장 오래된 서점 학문당과 40년이 넘은 헌책방 영록서점은 창동예술촌의 산증인이다. 작가들의 공방은 여행자의 체험공간이 되기도 한다. 도자기 만들기, 민화 그리기, 가훈 쓰기 등 다양한 체험거리가 마련돼 있다. 창동예술촌은 산책을 즐기기에도 좋다. 실핏줄처럼 이어진 좁은 골목이 정겹고, 아기자기한 벽화가 보는 이의 마음을 편하게 만든다."
    },
    {
      "courseDataId": 3,
      "title": "돝섬 해상 유원지",
      "text": "마산만에 그림 같이 자리한 돝섬은 섬 전체가 해상유원지로 조성되어 있으며 다양한 다양한 볼거리와 해양레포츠 체험등을 갖춘 친환경적인 가족공원이다. 돝섬해상유원지는 국내 최초의 해상유원지로 섬의 모양이 돼지 누운 모습이라 하여 돼지의 옛말인 ‘돝’을 따와 돝섬이라 불렀다는 전설이 전해지며 돝섬 내 산책로를 걷다 보면 백합나무와 팽나무 등의 웅장한 교목들을 만날 수 있고 해안산책로에서는 인근의 마산 시가지와 합포만의 전경을 감상할 수 있다."
    },
    {
      "courseDataId": 4,
      "title": "마산 어시장 횟집거리",
      "text": "마산 어시장 횟집거리는 경상남도 창원시 마산합포구 동성동과 남성동의 어시장 일대에 바다 생선회를 전문으로 하는 식당들이 밀집한 지역으로 마산의 활어회는 바다와 인접한 지리적 특성으로 남해안 청정해역에서 당일 잡아올린 선도 높은 생선을 저렴한 가격에 맛볼 수 있다. 어시장의 횟집에는 ‘봄 도다리, 가을 전어’식의 계절 생선들을 비롯하여 마산이 아니면 좀체 맛볼 수 없는 자연산 광어, 도미 등의 고급 어종들과 해산물이 수족관마다 살아 움직이고 있다.마산어시장 횟집은 수산물 원산지 표시 모범거리로 원산지의 정확한 정보를 제공함으로써 안전한 수산물 거래 활성화에 기여하고 있다."
    }
  ]
}
